tutorial_package_andschwe/greet.py
tutorial_package_andschwe/__init__.py
tutorial_package_andschwe-0.0.2.dist-info/DESCRIPTION.rst
tutorial_package_andschwe-0.0.2.dist-info/METADATA
tutorial_package_andschwe-0.0.2.dist-info/metadata.json
tutorial_package_andschwe-0.0.2.dist-info/RECORD
tutorial_package_andschwe-0.0.2.dist-info/top_level.txt
tutorial_package_andschwe-0.0.2.dist-info/WHEEL
